enjoysport/__init__.py
enjoysport/__main__.py
enjoysport/enjoysport.py
enjoysport-0.3.3.dist-info/METADATA
enjoysport-0.3.3.dist-info/WHEEL
enjoysport-0.3.3.dist-info/top_level.txt
enjoysport-0.3.3.dist-info/RECORD
