Metadata-Version: 2.1
Name: enjoysport
Version: 0.3.3
Summary: UNKNOWN
Home-page: UNKNOWN
Author: Arasu
Author-email: arasum6262@gmail.com
License: UNKNOWN
Platform: UNKNOWN
Requires-Dist: numpy
Requires-Dist: pandas
